ptforge/__init__.py
ptforge/core/__init__.py
ptforge/core/base.py
ptforge/core/config.py
ptforge/core/optimizer.py
ptforge/datasets/__init__.py
ptforge/datasets/loaders.py
ptforge/evaluators/__init__.py
ptforge/evaluators/evaluator.py
ptforge/llms/__init__.py
ptforge/llms/clients.py
ptforge/metrics/__init__.py
ptforge/metrics/implementations.py
ptforge/templates/__init__.py
ptforge/templates/base_template.py
ptforge/templates/factory.py
ptforge/templates/builtins/__init__.py
ptforge/templates/builtins/ape.py
ptforge/templates/builtins/broke.py
ptforge/templates/builtins/crispe.py
ptforge/templates/builtins/rctcre.py
ptforge/updaters/__init__.py
ptforge/updaters/base_updater.py
ptforge/updaters/llm_updater.py
ptforge/utils/__init__.py
ptforge-0.1.4.dist-info/licenses/LICENSE
ptforge-0.1.4.dist-info/METADATA
ptforge-0.1.4.dist-info/WHEEL
ptforge-0.1.4.dist-info/top_level.txt
ptforge-0.1.4.dist-info/RECORD
